fastapi_xml/__init__.py
fastapi_xml/decoder.py
fastapi_xml/openapi.py
fastapi_xml/py.typed
fastapi_xml/response.py
fastapi_xml/route.py
fastapi_xml/xmlbody.py
fastapi_xml-1.1.1.dist-info/LICENSE
fastapi_xml-1.1.1.dist-info/METADATA
fastapi_xml-1.1.1.dist-info/WHEEL
fastapi_xml-1.1.1.dist-info/RECORD
