Metadata-Version: 2.1
Name: fastapi-xml
Version: 1.1.1
Summary: adds xml support to fastapi
Home-page: https://github.com/cercide/fastapi-xml
License: MIT
Author: Leon Rendel
Author-email: cercide@tuta.io
Maintainer: Leon Rendel
Maintainer-email: cercide@tuta.io
Requires-Python: >=3.9,<4.0
Classifier: Framework :: FastAPI
Classifier: License :: OSI Approved :: MIT License
Classifier: Programming Language :: Python :: 3
Classifier: Programming Language :: Python :: 3.9
Classifier: Programming Language :: Python :: 3.10
Classifier: Programming Language :: Python :: 3.11
Classifier: Programming Language :: Python :: 3.12
Classifier: Topic :: Software Development :: Libraries :: Python Modules
Classifier: Topic :: Text Processing :: Markup :: XML
Requires-Dist: fastapi (>=0.113.0)
Requires-Dist: pydantic (>=2.0)
Requires-Dist: xsdata (>=22.9)
Project-URL: Repository, https://github.com/cercide/fastapi-xml
